password_analyzer/__init__.py
password_analyzer/analyzer_options.py
password_analyzer/constants.py
password_analyzer/password_analyzer.py
password_analyzer/password_review.py
password_analyzer/validators.py
password_analyzer-0.1.0.dist-info/METADATA
password_analyzer-0.1.0.dist-info/WHEEL
password_analyzer-0.1.0.dist-info/licenses/LICENSE
password_analyzer-0.1.0.dist-info/RECORD
